setup.py
dsdn_distribution_sc/Binomialdistribution.py
dsdn_distribution_sc/Gaussiandistribution.py
dsdn_distribution_sc/Generaldistribution.py
dsdn_distribution_sc/__init__.py
dsdn_distribution_sc.egg-info/PKG-INFO
dsdn_distribution_sc.egg-info/SOURCES.txt
dsdn_distribution_sc.egg-info/dependency_links.txt
dsdn_distribution_sc.egg-info/not-zip-safe
dsdn_distribution_sc.egg-info/top_level.txt