Metadata-Version: 1.0
Name: dsdn-distribution-sc
Version: 0.1
Summary: Distributions
Home-page: UNKNOWN
Author: Sonali Chawla
Author-email: sc@gmail.com
License: UNKNOWN
Platform: UNKNOWN
